Workbook

Sheet Summary
C2: Nokia DCF Valuation
C3: Illustrative student model based on a point-in-time valuation exercise
C6: Valuation Summary | D6: Valuation Summary | E6: Valuation Summary | F6: Valuation Summary | G6: Valuation Summary | H6: Valuation Summary
C7: Enterprise value | D7: ='DCF Model'!D24 -> 29773.379
C8: Net cash | D8: =Assumptions!D10 -> 6944
C9: Equity value | D9: ='DCF Model'!D26 -> 36717.379
C10: Diluted shares | D10: =Assumptions!D9 -> 5600
C11: Implied value per share | D11: ='DCF Model'!D28 -> 6.5566749
C12: Upside or downside | D12: ='DCF Model'!D29 -> -0.45361043
C15: Model Takeaways | D15: Model Takeaways | E15: Model Takeaways | F15: Model Takeaways | G15: Model Takeaways | H15: Model Takeaways
C16: The model values Nokia from forecast unlevered free cash flow and a perpetual-growth terminal value. The main output is highly sensitive to WACC and terminal growth, so the Sensitivity tab should be reviewed with the base result. All yellow cells on the Assumptions tab are editable. | D16: The model values Nokia from forecast unlevered free cash flow and a perpetual-growth terminal value. The main output is highly sensitive to WACC and terminal growth, so the Sensitivity tab should be reviewed with the base result. All yellow cells on the Assumptions tab are editable. | E16: The model values Nokia from forecast unlevered free cash flow and a perpetual-growth terminal value. The main output is highly sensitive to WACC and terminal growth, so the Sensitivity tab should be reviewed with the base result. All yellow cells on the Assumptions tab are editable. | F16: The model values Nokia from forecast unlevered free cash flow and a perpetual-growth terminal value. The main output is highly sensitive to WACC and terminal growth, so the Sensitivity tab should be reviewed with the base result. All yellow cells on the Assumptions tab are editable. | G16: The model values Nokia from forecast unlevered free cash flow and a perpetual-growth terminal value. The main output is highly sensitive to WACC and terminal growth, so the Sensitivity tab should be reviewed with the base result. All yellow cells on the Assumptions tab are editable. | H16: The model values Nokia from forecast unlevered free cash flow and a perpetual-growth terminal value. The main output is highly sensitive to WACC and terminal growth, so the Sensitivity tab should be reviewed with the base result. All yellow cells on the Assumptions tab are editable.
C17: The model values Nokia from forecast unlevered free cash flow and a perpetual-growth terminal value. The main output is highly sensitive to WACC and terminal growth, so the Sensitivity tab should be reviewed with the base result. All yellow cells on the Assumptions tab are editable. | D17: The model values Nokia from forecast unlevered free cash flow and a perpetual-growth terminal value. The main output is highly sensitive to WACC and terminal growth, so the Sensitivity tab should be reviewed with the base result. All yellow cells on the Assumptions tab are editable. | E17: The model values Nokia from forecast unlevered free cash flow and a perpetual-growth terminal value. The main output is highly sensitive to WACC and terminal growth, so the Sensitivity tab should be reviewed with the base result. All yellow cells on the Assumptions tab are editable. | F17: The model values Nokia from forecast unlevered free cash flow and a perpetual-growth terminal value. The main output is highly sensitive to WACC and terminal growth, so the Sensitivity tab should be reviewed with the base result. All yellow cells on the Assumptions tab are editable. | G17: The model values Nokia from forecast unlevered free cash flow and a perpetual-growth terminal value. The main output is highly sensitive to WACC and terminal growth, so the Sensitivity tab should be reviewed with the base result. All yellow cells on the Assumptions tab are editable. | H17: The model values Nokia from forecast unlevered free cash flow and a perpetual-growth terminal value. The main output is highly sensitive to WACC and terminal growth, so the Sensitivity tab should be reviewed with the base result. All yellow cells on the Assumptions tab are editable.
C18: The model values Nokia from forecast unlevered free cash flow and a perpetual-growth terminal value. The main output is highly sensitive to WACC and terminal growth, so the Sensitivity tab should be reviewed with the base result. All yellow cells on the Assumptions tab are editable. | D18: The model values Nokia from forecast unlevered free cash flow and a perpetual-growth terminal value. The main output is highly sensitive to WACC and terminal growth, so the Sensitivity tab should be reviewed with the base result. All yellow cells on the Assumptions tab are editable. | E18: The model values Nokia from forecast unlevered free cash flow and a perpetual-growth terminal value. The main output is highly sensitive to WACC and terminal growth, so the Sensitivity tab should be reviewed with the base result. All yellow cells on the Assumptions tab are editable. | F18: The model values Nokia from forecast unlevered free cash flow and a perpetual-growth terminal value. The main output is highly sensitive to WACC and terminal growth, so the Sensitivity tab should be reviewed with the base result. All yellow cells on the Assumptions tab are editable. | G18: The model values Nokia from forecast unlevered free cash flow and a perpetual-growth terminal value. The main output is highly sensitive to WACC and terminal growth, so the Sensitivity tab should be reviewed with the base result. All yellow cells on the Assumptions tab are editable. | H18: The model values Nokia from forecast unlevered free cash flow and a perpetual-growth terminal value. The main output is highly sensitive to WACC and terminal growth, so the Sensitivity tab should be reviewed with the base result. All yellow cells on the Assumptions tab are editable.
C19: The model values Nokia from forecast unlevered free cash flow and a perpetual-growth terminal value. The main output is highly sensitive to WACC and terminal growth, so the Sensitivity tab should be reviewed with the base result. All yellow cells on the Assumptions tab are editable. | D19: The model values Nokia from forecast unlevered free cash flow and a perpetual-growth terminal value. The main output is highly sensitive to WACC and terminal growth, so the Sensitivity tab should be reviewed with the base result. All yellow cells on the Assumptions tab are editable. | E19: The model values Nokia from forecast unlevered free cash flow and a perpetual-growth terminal value. The main output is highly sensitive to WACC and terminal growth, so the Sensitivity tab should be reviewed with the base result. All yellow cells on the Assumptions tab are editable. | F19: The model values Nokia from forecast unlevered free cash flow and a perpetual-growth terminal value. The main output is highly sensitive to WACC and terminal growth, so the Sensitivity tab should be reviewed with the base result. All yellow cells on the Assumptions tab are editable. | G19: The model values Nokia from forecast unlevered free cash flow and a perpetual-growth terminal value. The main output is highly sensitive to WACC and terminal growth, so the Sensitivity tab should be reviewed with the base result. All yellow cells on the Assumptions tab are editable. | H19: The model values Nokia from forecast unlevered free cash flow and a perpetual-growth terminal value. The main output is highly sensitive to WACC and terminal growth, so the Sensitivity tab should be reviewed with the base result. All yellow cells on the Assumptions tab are editable.

Sheet Assumptions
C2: Nokia DCF Assumptions
C3: Yellow cells are editable analyst inputs; monetary figures are in EUR millions except per-share data
C6: Company and Valuation Inputs | D6: Company and Valuation Inputs | E6: Company and Valuation Inputs | F6: Company and Valuation Inputs | G6: Company and Valuation Inputs | H6: Company and Valuation Inputs
C7: Input | D7: Value | E7: Basis
C8: Current share price | D8: 12 | E8: Training exercise input
C9: Diluted shares | D9: 5600 | E9: Implied by EUR 67.2bn equity value at EUR 12.00 per share
C10: Net cash | D10: 6944 | E10: Equity value less enterprise value in the exercise
C11: Base year revenue | D11: 19220 | E11: Illustrative starting point
C12: Base year EBIT margin | D12: 0.1 | E12: Illustrative starting point
C15: Forecast Assumptions | D15: Forecast Assumptions | E15: Forecast Assumptions | F15: Forecast Assumptions | G15: Forecast Assumptions | H15: Forecast Assumptions | I15: Forecast Assumptions
C16: Driver | D16: 2025A | E16: 2026E | F16: 2027E | G16: 2028E | H16: 2029E | I16: 2030E
C17: Revenue growth | E17: 0.03 | F17: 0.035 | G17: 0.04 | H17: 0.04 | I17: 0.035
C18: EBIT margin | D18: 0.1 | E18: 0.105 | F18: 0.11 | G18: 0.115 | H18: 0.118 | I18: 0.12
C19: D&A as % of revenue | D19: 0.03 | E19: 0.03 | F19: 0.03 | G19: 0.03 | H19: 0.03 | I19: 0.03
C20: Capital expenditures as % of revenue | D20: 0.032 | E20: 0.032 | F20: 0.032 | G20: 0.032 | H20: 0.032 | I20: 0.032
C21: Change in NWC as % of revenue | D21: 0.005 | E21: 0.005 | F21: 0.005 | G21: 0.005 | H21: 0.005 | I21: 0.005
C22: Cash tax rate | D22: 0.21 | E22: 0.21 | F22: 0.21 | G22: 0.21 | H22: 0.21 | I22: 0.21
C25: Terminal Value Inputs | D25: Terminal Value Inputs | E25: Terminal Value Inputs
C26: Input | D26: Value | E26: Method
C27: WACC | D27: 0.085 | E27: Discount rate
C28: Terminal growth rate | D28: 0.025 | E28: Perpetual growth
C31: Sources and Scope | D31: Sources and Scope | E31: Sources and Scope | F31: Sources and Scope | G31: Sources and Scope | H31: Sources and Scope | I31: Sources and Scope
C32: Public reference: Nokia 2025 Annual Report and investor reports at https://www.nokia.com/about-us/investors/results-reports/. The current share price, diluted equity value, enterprise value bridge, and share count are based on the user's point-in-time valuation training exercise. Forecast growth, margins, reinvestment, WACC, and terminal growth are editable analyst assumptions created for this illustrative model. | D32: Public reference: Nokia 2025 Annual Report and investor reports at https://www.nokia.com/about-us/investors/results-reports/. The current share price, diluted equity value, enterprise value bridge, and share count are based on the user's point-in-time valuation training exercise. Forecast growth, margins, reinvestment, WACC, and terminal growth are editable analyst assumptions created for this illustrative model. | E32: Public reference: Nokia 2025 Annual Report and investor reports at https://www.nokia.com/about-us/investors/results-reports/. The current share price, diluted equity value, enterprise value bridge, and share count are based on the user's point-in-time valuation training exercise. Forecast growth, margins, reinvestment, WACC, and terminal growth are editable analyst assumptions created for this illustrative model. | F32: Public reference: Nokia 2025 Annual Report and investor reports at https://www.nokia.com/about-us/investors/results-reports/. The current share price, diluted equity value, enterprise value bridge, and share count are based on the user's point-in-time valuation training exercise. Forecast growth, margins, reinvestment, WACC, and terminal growth are editable analyst assumptions created for this illustrative model. | G32: Public reference: Nokia 2025 Annual Report and investor reports at https://www.nokia.com/about-us/investors/results-reports/. The current share price, diluted equity value, enterprise value bridge, and share count are based on the user's point-in-time valuation training exercise. Forecast growth, margins, reinvestment, WACC, and terminal growth are editable analyst assumptions created for this illustrative model. | H32: Public reference: Nokia 2025 Annual Report and investor reports at https://www.nokia.com/about-us/investors/results-reports/. The current share price, diluted equity value, enterprise value bridge, and share count are based on the user's point-in-time valuation training exercise. Forecast growth, margins, reinvestment, WACC, and terminal growth are editable analyst assumptions created for this illustrative model. | I32: Public reference: Nokia 2025 Annual Report and investor reports at https://www.nokia.com/about-us/investors/results-reports/. The current share price, diluted equity value, enterprise value bridge, and share count are based on the user's point-in-time valuation training exercise. Forecast growth, margins, reinvestment, WACC, and terminal growth are editable analyst assumptions created for this illustrative model.
C33: Public reference: Nokia 2025 Annual Report and investor reports at https://www.nokia.com/about-us/investors/results-reports/. The current share price, diluted equity value, enterprise value bridge, and share count are based on the user's point-in-time valuation training exercise. Forecast growth, margins, reinvestment, WACC, and terminal growth are editable analyst assumptions created for this illustrative model. | D33: Public reference: Nokia 2025 Annual Report and investor reports at https://www.nokia.com/about-us/investors/results-reports/. The current share price, diluted equity value, enterprise value bridge, and share count are based on the user's point-in-time valuation training exercise. Forecast growth, margins, reinvestment, WACC, and terminal growth are editable analyst assumptions created for this illustrative model. | E33: Public reference: Nokia 2025 Annual Report and investor reports at https://www.nokia.com/about-us/investors/results-reports/. The current share price, diluted equity value, enterprise value bridge, and share count are based on the user's point-in-time valuation training exercise. Forecast growth, margins, reinvestment, WACC, and terminal growth are editable analyst assumptions created for this illustrative model. | F33: Public reference: Nokia 2025 Annual Report and investor reports at https://www.nokia.com/about-us/investors/results-reports/. The current share price, diluted equity value, enterprise value bridge, and share count are based on the user's point-in-time valuation training exercise. Forecast growth, margins, reinvestment, WACC, and terminal growth are editable analyst assumptions created for this illustrative model. | G33: Public reference: Nokia 2025 Annual Report and investor reports at https://www.nokia.com/about-us/investors/results-reports/. The current share price, diluted equity value, enterprise value bridge, and share count are based on the user's point-in-time valuation training exercise. Forecast growth, margins, reinvestment, WACC, and terminal growth are editable analyst assumptions created for this illustrative model. | H33: Public reference: Nokia 2025 Annual Report and investor reports at https://www.nokia.com/about-us/investors/results-reports/. The current share price, diluted equity value, enterprise value bridge, and share count are based on the user's point-in-time valuation training exercise. Forecast growth, margins, reinvestment, WACC, and terminal growth are editable analyst assumptions created for this illustrative model. | I33: Public reference: Nokia 2025 Annual Report and investor reports at https://www.nokia.com/about-us/investors/results-reports/. The current share price, diluted equity value, enterprise value bridge, and share count are based on the user's point-in-time valuation training exercise. Forecast growth, margins, reinvestment, WACC, and terminal growth are editable analyst assumptions created for this illustrative model.
C34: Public reference: Nokia 2025 Annual Report and investor reports at https://www.nokia.com/about-us/investors/results-reports/. The current share price, diluted equity value, enterprise value bridge, and share count are based on the user's point-in-time valuation training exercise. Forecast growth, margins, reinvestment, WACC, and terminal growth are editable analyst assumptions created for this illustrative model. | D34: Public reference: Nokia 2025 Annual Report and investor reports at https://www.nokia.com/about-us/investors/results-reports/. The current share price, diluted equity value, enterprise value bridge, and share count are based on the user's point-in-time valuation training exercise. Forecast growth, margins, reinvestment, WACC, and terminal growth are editable analyst assumptions created for this illustrative model. | E34: Public reference: Nokia 2025 Annual Report and investor reports at https://www.nokia.com/about-us/investors/results-reports/. The current share price, diluted equity value, enterprise value bridge, and share count are based on the user's point-in-time valuation training exercise. Forecast growth, margins, reinvestment, WACC, and terminal growth are editable analyst assumptions created for this illustrative model. | F34: Public reference: Nokia 2025 Annual Report and investor reports at https://www.nokia.com/about-us/investors/results-reports/. The current share price, diluted equity value, enterprise value bridge, and share count are based on the user's point-in-time valuation training exercise. Forecast growth, margins, reinvestment, WACC, and terminal growth are editable analyst assumptions created for this illustrative model. | G34: Public reference: Nokia 2025 Annual Report and investor reports at https://www.nokia.com/about-us/investors/results-reports/. The current share price, diluted equity value, enterprise value bridge, and share count are based on the user's point-in-time valuation training exercise. Forecast growth, margins, reinvestment, WACC, and terminal growth are editable analyst assumptions created for this illustrative model. | H34: Public reference: Nokia 2025 Annual Report and investor reports at https://www.nokia.com/about-us/investors/results-reports/. The current share price, diluted equity value, enterprise value bridge, and share count are based on the user's point-in-time valuation training exercise. Forecast growth, margins, reinvestment, WACC, and terminal growth are editable analyst assumptions created for this illustrative model. | I34: Public reference: Nokia 2025 Annual Report and investor reports at https://www.nokia.com/about-us/investors/results-reports/. The current share price, diluted equity value, enterprise value bridge, and share count are based on the user's point-in-time valuation training exercise. Forecast growth, margins, reinvestment, WACC, and terminal growth are editable analyst assumptions created for this illustrative model.
C35: Public reference: Nokia 2025 Annual Report and investor reports at https://www.nokia.com/about-us/investors/results-reports/. The current share price, diluted equity value, enterprise value bridge, and share count are based on the user's point-in-time valuation training exercise. Forecast growth, margins, reinvestment, WACC, and terminal growth are editable analyst assumptions created for this illustrative model. | D35: Public reference: Nokia 2025 Annual Report and investor reports at https://www.nokia.com/about-us/investors/results-reports/. The current share price, diluted equity value, enterprise value bridge, and share count are based on the user's point-in-time valuation training exercise. Forecast growth, margins, reinvestment, WACC, and terminal growth are editable analyst assumptions created for this illustrative model. | E35: Public reference: Nokia 2025 Annual Report and investor reports at https://www.nokia.com/about-us/investors/results-reports/. The current share price, diluted equity value, enterprise value bridge, and share count are based on the user's point-in-time valuation training exercise. Forecast growth, margins, reinvestment, WACC, and terminal growth are editable analyst assumptions created for this illustrative model. | F35: Public reference: Nokia 2025 Annual Report and investor reports at https://www.nokia.com/about-us/investors/results-reports/. The current share price, diluted equity value, enterprise value bridge, and share count are based on the user's point-in-time valuation training exercise. Forecast growth, margins, reinvestment, WACC, and terminal growth are editable analyst assumptions created for this illustrative model. | G35: Public reference: Nokia 2025 Annual Report and investor reports at https://www.nokia.com/about-us/investors/results-reports/. The current share price, diluted equity value, enterprise value bridge, and share count are based on the user's point-in-time valuation training exercise. Forecast growth, margins, reinvestment, WACC, and terminal growth are editable analyst assumptions created for this illustrative model. | H35: Public reference: Nokia 2025 Annual Report and investor reports at https://www.nokia.com/about-us/investors/results-reports/. The current share price, diluted equity value, enterprise value bridge, and share count are based on the user's point-in-time valuation training exercise. Forecast growth, margins, reinvestment, WACC, and terminal growth are editable analyst assumptions created for this illustrative model. | I35: Public reference: Nokia 2025 Annual Report and investor reports at https://www.nokia.com/about-us/investors/results-reports/. The current share price, diluted equity value, enterprise value bridge, and share count are based on the user's point-in-time valuation training exercise. Forecast growth, margins, reinvestment, WACC, and terminal growth are editable analyst assumptions created for this illustrative model.
C36: Public reference: Nokia 2025 Annual Report and investor reports at https://www.nokia.com/about-us/investors/results-reports/. The current share price, diluted equity value, enterprise value bridge, and share count are based on the user's point-in-time valuation training exercise. Forecast growth, margins, reinvestment, WACC, and terminal growth are editable analyst assumptions created for this illustrative model. | D36: Public reference: Nokia 2025 Annual Report and investor reports at https://www.nokia.com/about-us/investors/results-reports/. The current share price, diluted equity value, enterprise value bridge, and share count are based on the user's point-in-time valuation training exercise. Forecast growth, margins, reinvestment, WACC, and terminal growth are editable analyst assumptions created for this illustrative model. | E36: Public reference: Nokia 2025 Annual Report and investor reports at https://www.nokia.com/about-us/investors/results-reports/. The current share price, diluted equity value, enterprise value bridge, and share count are based on the user's point-in-time valuation training exercise. Forecast growth, margins, reinvestment, WACC, and terminal growth are editable analyst assumptions created for this illustrative model. | F36: Public reference: Nokia 2025 Annual Report and investor reports at https://www.nokia.com/about-us/investors/results-reports/. The current share price, diluted equity value, enterprise value bridge, and share count are based on the user's point-in-time valuation training exercise. Forecast growth, margins, reinvestment, WACC, and terminal growth are editable analyst assumptions created for this illustrative model. | G36: Public reference: Nokia 2025 Annual Report and investor reports at https://www.nokia.com/about-us/investors/results-reports/. The current share price, diluted equity value, enterprise value bridge, and share count are based on the user's point-in-time valuation training exercise. Forecast growth, margins, reinvestment, WACC, and terminal growth are editable analyst assumptions created for this illustrative model. | H36: Public reference: Nokia 2025 Annual Report and investor reports at https://www.nokia.com/about-us/investors/results-reports/. The current share price, diluted equity value, enterprise value bridge, and share count are based on the user's point-in-time valuation training exercise. Forecast growth, margins, reinvestment, WACC, and terminal growth are editable analyst assumptions created for this illustrative model. | I36: Public reference: Nokia 2025 Annual Report and investor reports at https://www.nokia.com/about-us/investors/results-reports/. The current share price, diluted equity value, enterprise value bridge, and share count are based on the user's point-in-time valuation training exercise. Forecast growth, margins, reinvestment, WACC, and terminal growth are editable analyst assumptions created for this illustrative model.

Sheet DCF Model
C2: Nokia Discounted Cash Flow Model
C3: Unlevered free cash flow valuation in EUR millions except per-share data
C6: Metric | D6: 2025A | E6: 2026E | F6: 2027E | G6: 2028E | H6: 2029E | I6: 2030E
C7: Revenue | D7: =Assumptions!D11 -> 19220 | E7: =D7*(1+E8) -> 19796.6 | F7: =E7*(1+F8) -> 20489.481 | G7: =F7*(1+G8) -> 21309.06 | H7: =G7*(1+H8) -> 22161.423 | I7: =H7*(1+I8) -> 22937.072
C8: Revenue growth | D8: =Assumptions!D17 -> 0 | E8: =Assumptions!E17 -> 0.03 | F8: =Assumptions!F17 -> 0.035 | G8: =Assumptions!G17 -> 0.04 | H8: =Assumptions!H17 -> 0.04 | I8: =Assumptions!I17 -> 0.035
C9: EBIT margin | D9: =Assumptions!D18 -> 0.1 | E9: =Assumptions!E18 -> 0.105 | F9: =Assumptions!F18 -> 0.11 | G9: =Assumptions!G18 -> 0.115 | H9: =Assumptions!H18 -> 0.118 | I9: =Assumptions!I18 -> 0.12
C10: EBIT | D10: =D7*D9 -> 1922 | E10: =E7*E9 -> 2078.643 | F10: =F7*F9 -> 2253.8429 | G10: =G7*G9 -> 2450.5419 | H10: =H7*H9 -> 2615.0479 | I10: =I7*I9 -> 2752.4487
C11: Cash taxes | D11: =-D10*Assumptions!D22 -> -403.62 | E11: =-E10*Assumptions!E22 -> -436.51503 | F11: =-F10*Assumptions!F22 -> -473.30701 | G11: =-G10*Assumptions!G22 -> -514.6138 | H11: =-H10*Assumptions!H22 -> -549.16005 | I11: =-I10*Assumptions!I22 -> -578.01423
C12: NOPAT | D12: =D10+D11 -> 1518.38 | E12: =E10+E11 -> 1642.128 | F12: =F10+F11 -> 1780.5359 | G12: =G10+G11 -> 1935.9281 | H12: =H10+H11 -> 2065.8878 | I12: =I10+I11 -> 2174.4345
C13: D&A | D13: =D7*Assumptions!D19 -> 576.6 | E13: =E7*Assumptions!E19 -> 593.898 | F13: =F7*Assumptions!F19 -> 614.68443 | G13: =G7*Assumptions!G19 -> 639.27181 | H13: =H7*Assumptions!H19 -> 664.84268 | I13: =I7*Assumptions!I19 -> 688.11217
C14: Capital expenditures | D14: =-D7*Assumptions!D20 -> -615.04 | E14: =-E7*Assumptions!E20 -> -633.4912 | F14: =-F7*Assumptions!F20 -> -655.66339 | G14: =-G7*Assumptions!G20 -> -681.88993 | H14: =-H7*Assumptions!H20 -> -709.16552 | I14: =-I7*Assumptions!I20 -> -733.98632
C15: Change in NWC | D15: =-D7*Assumptions!D21 -> -96.1 | E15: =-E7*Assumptions!E21 -> -98.983 | F15: =-F7*Assumptions!F21 -> -102.44741 | G15: =-G7*Assumptions!G21 -> -106.5453 | H15: =-H7*Assumptions!H21 -> -110.80711 | I15: =-I7*Assumptions!I21 -> -114.68536
C16: Unlevered free cash flow | D16: =D12+D13+D14+D15 -> 1383.84 | E16: =E12+E13+E14+E15 -> 1503.5518 | F16: =F12+F13+F14+F15 -> 1637.1095 | G16: =G12+G13+G14+G15 -> 1786.7647 | H16: =H12+H13+H14+H15 -> 1910.7579 | I16: =I12+I13+I14+I15 -> 2013.875
C17: Discount period | D17: 0 | E17: 1 | F17: 2 | G17: 3 | H17: 4 | I17: 5
C18: Discount factor | D18: =1 -> 1 | E18: =1/(1+Assumptions!$D$27)^E17 -> 0.92165899 | F18: =1/(1+Assumptions!$D$27)^F17 -> 0.84945529 | G18: =1/(1+Assumptions!$D$27)^G17 -> 0.7829081 | H18: =1/(1+Assumptions!$D$27)^H17 -> 0.72157428 | I18: =1/(1+Assumptions!$D$27)^I17 -> 0.66504542
C21: Valuation Bridge | D21: Valuation Bridge | E21: Valuation Bridge | F21: Valuation Bridge
C22: PV of forecast free cash flow | D22: =SUMPRODUCT(E16:I16,E18:I18) -> 6893.358
C23: PV of terminal value | D23: =(I16*(1+Assumptions!$D$28)/(Assumptions!$D$27-Assumptions!$D$28))*I18 -> 22880.021
C24: Enterprise value | D24: =SUM(D22:D23) -> 29773.379
C25: Net cash | D25: =Assumptions!D10 -> 6944
C26: Equity value | D26: =D24+D25 -> 36717.379
C27: Diluted shares | D27: =Assumptions!D9 -> 5600
C28: Implied value per share | D28: =D26/D27 -> 6.5566749
C29: Upside or downside | D29: =D28/Assumptions!D8-1 -> -0.45361043
C30: Terminal value as % of EV | D30: =D23/D24 -> 0.76847244
C31: Current share price | D31: =Assumptions!D8 -> 12

Sheet Sensitivity
C2: DCF Sensitivity Analysis
C3: Implied value per share across WACC and terminal-growth assumptions
C6: WACC and Terminal Growth | D6: WACC and Terminal Growth | E6: WACC and Terminal Growth | F6: WACC and Terminal Growth | G6: WACC and Terminal Growth | H6: WACC and Terminal Growth | I6: WACC and Terminal Growth
C7: WACC / Growth | D7: 0.015 | E7: 0.02 | F7: 0.025 | G7: 0.03 | H7: 0.035
C8: 0.075 | D8: =('DCF Model'!$E$16/(1+$C8)^1+'DCF Model'!$F$16/(1+$C8)^2+'DCF Model'!$G$16/(1+$C8)^3+'DCF Model'!$H$16/(1+$C8)^4+'DCF Model'!$I$16/(1+$C8)^5+('DCF Model'!$I$16*(1+D$7)/($C8-D$7))/(1+$C8)^5+Assumptions!$D$10)/Assumptions!$D$9 -> 6.7431296 | E8: =('DCF Model'!$E$16/(1+$C8)^1+'DCF Model'!$F$16/(1+$C8)^2+'DCF Model'!$G$16/(1+$C8)^3+'DCF Model'!$H$16/(1+$C8)^4+'DCF Model'!$I$16/(1+$C8)^5+('DCF Model'!$I$16*(1+E$7)/($C8-E$7))/(1+$C8)^5+Assumptions!$D$10)/Assumptions!$D$9 -> 7.1511358 | F8: =('DCF Model'!$E$16/(1+$C8)^1+'DCF Model'!$F$16/(1+$C8)^2+'DCF Model'!$G$16/(1+$C8)^3+'DCF Model'!$H$16/(1+$C8)^4+'DCF Model'!$I$16/(1+$C8)^5+('DCF Model'!$I$16*(1+F$7)/($C8-F$7))/(1+$C8)^5+Assumptions!$D$10)/Assumptions!$D$9 -> 7.6407431 | G8: =('DCF Model'!$E$16/(1+$C8)^1+'DCF Model'!$F$16/(1+$C8)^2+'DCF Model'!$G$16/(1+$C8)^3+'DCF Model'!$H$16/(1+$C8)^4+'DCF Model'!$I$16/(1+$C8)^5+('DCF Model'!$I$16*(1+G$7)/($C8-G$7))/(1+$C8)^5+Assumptions!$D$10)/Assumptions!$D$9 -> 8.2391521 | H8: =('DCF Model'!$E$16/(1+$C8)^1+'DCF Model'!$F$16/(1+$C8)^2+'DCF Model'!$G$16/(1+$C8)^3+'DCF Model'!$H$16/(1+$C8)^4+'DCF Model'!$I$16/(1+$C8)^5+('DCF Model'!$I$16*(1+H$7)/($C8-H$7))/(1+$C8)^5+Assumptions!$D$10)/Assumptions!$D$9 -> 8.9871633
C9: 0.08 | D9: =('DCF Model'!$E$16/(1+$C9)^1+'DCF Model'!$F$16/(1+$C9)^2+'DCF Model'!$G$16/(1+$C9)^3+'DCF Model'!$H$16/(1+$C9)^4+'DCF Model'!$I$16/(1+$C9)^5+('DCF Model'!$I$16*(1+D$7)/($C9-D$7))/(1+$C9)^5+Assumptions!$D$10)/Assumptions!$D$9 -> 6.3099632 | E9: =('DCF Model'!$E$16/(1+$C9)^1+'DCF Model'!$F$16/(1+$C9)^2+'DCF Model'!$G$16/(1+$C9)^3+'DCF Model'!$H$16/(1+$C9)^4+'DCF Model'!$I$16/(1+$C9)^5+('DCF Model'!$I$16*(1+E$7)/($C9-E$7))/(1+$C9)^5+Assumptions!$D$10)/Assumptions!$D$9 -> 6.6488502 | F9: =('DCF Model'!$E$16/(1+$C9)^1+'DCF Model'!$F$16/(1+$C9)^2+'DCF Model'!$G$16/(1+$C9)^3+'DCF Model'!$H$16/(1+$C9)^4+'DCF Model'!$I$16/(1+$C9)^5+('DCF Model'!$I$16*(1+F$7)/($C9-F$7))/(1+$C9)^5+Assumptions!$D$10)/Assumptions!$D$9 -> 7.0493529 | G9: =('DCF Model'!$E$16/(1+$C9)^1+'DCF Model'!$F$16/(1+$C9)^2+'DCF Model'!$G$16/(1+$C9)^3+'DCF Model'!$H$16/(1+$C9)^4+'DCF Model'!$I$16/(1+$C9)^5+('DCF Model'!$I$16*(1+G$7)/($C9-G$7))/(1+$C9)^5+Assumptions!$D$10)/Assumptions!$D$9 -> 7.5299562 | H9: =('DCF Model'!$E$16/(1+$C9)^1+'DCF Model'!$F$16/(1+$C9)^2+'DCF Model'!$G$16/(1+$C9)^3+'DCF Model'!$H$16/(1+$C9)^4+'DCF Model'!$I$16/(1+$C9)^5+('DCF Model'!$I$16*(1+H$7)/($C9-H$7))/(1+$C9)^5+Assumptions!$D$10)/Assumptions!$D$9 -> 8.1173603
C10: 0.085 | D10: =('DCF Model'!$E$16/(1+$C10)^1+'DCF Model'!$F$16/(1+$C10)^2+'DCF Model'!$G$16/(1+$C10)^3+'DCF Model'!$H$16/(1+$C10)^4+'DCF Model'!$I$16/(1+$C10)^5+('DCF Model'!$I$16*(1+D$7)/($C10-D$7))/(1+$C10)^5+Assumptions!$D$10)/Assumptions!$D$9 -> 5.9388346 | E10: =('DCF Model'!$E$16/(1+$C10)^1+'DCF Model'!$F$16/(1+$C10)^2+'DCF Model'!$G$16/(1+$C10)^3+'DCF Model'!$H$16/(1+$C10)^4+'DCF Model'!$I$16/(1+$C10)^5+('DCF Model'!$I$16*(1+E$7)/($C10-E$7))/(1+$C10)^5+Assumptions!$D$10)/Assumptions!$D$9 -> 6.2239916 | F10: =('DCF Model'!$E$16/(1+$C10)^1+'DCF Model'!$F$16/(1+$C10)^2+'DCF Model'!$G$16/(1+$C10)^3+'DCF Model'!$H$16/(1+$C10)^4+'DCF Model'!$I$16/(1+$C10)^5+('DCF Model'!$I$16*(1+F$7)/($C10-F$7))/(1+$C10)^5+Assumptions!$D$10)/Assumptions!$D$9 -> 6.5566749 | G10: =('DCF Model'!$E$16/(1+$C10)^1+'DCF Model'!$F$16/(1+$C10)^2+'DCF Model'!$G$16/(1+$C10)^3+'DCF Model'!$H$16/(1+$C10)^4+'DCF Model'!$I$16/(1+$C10)^5+('DCF Model'!$I$16*(1+G$7)/($C10-G$7))/(1+$C10)^5+Assumptions!$D$10)/Assumptions!$D$9 -> 6.949846 | H10: =('DCF Model'!$E$16/(1+$C10)^1+'DCF Model'!$F$16/(1+$C10)^2+'DCF Model'!$G$16/(1+$C10)^3+'DCF Model'!$H$16/(1+$C10)^4+'DCF Model'!$I$16/(1+$C10)^5+('DCF Model'!$I$16*(1+H$7)/($C10-H$7))/(1+$C10)^5+Assumptions!$D$10)/Assumptions!$D$9 -> 7.4216513
C11: 0.09 | D11: =('DCF Model'!$E$16/(1+$C11)^1+'DCF Model'!$F$16/(1+$C11)^2+'DCF Model'!$G$16/(1+$C11)^3+'DCF Model'!$H$16/(1+$C11)^4+'DCF Model'!$I$16/(1+$C11)^5+('DCF Model'!$I$16*(1+D$7)/($C11-D$7))/(1+$C11)^5+Assumptions!$D$10)/Assumptions!$D$9 -> 5.6173329 | E11: =('DCF Model'!$E$16/(1+$C11)^1+'DCF Model'!$F$16/(1+$C11)^2+'DCF Model'!$G$16/(1+$C11)^3+'DCF Model'!$H$16/(1+$C11)^4+'DCF Model'!$I$16/(1+$C11)^5+('DCF Model'!$I$16*(1+E$7)/($C11-E$7))/(1+$C11)^5+Assumptions!$D$10)/Assumptions!$D$9 -> 5.8599655 | F11: =('DCF Model'!$E$16/(1+$C11)^1+'DCF Model'!$F$16/(1+$C11)^2+'DCF Model'!$G$16/(1+$C11)^3+'DCF Model'!$H$16/(1+$C11)^4+'DCF Model'!$I$16/(1+$C11)^5+('DCF Model'!$I$16*(1+F$7)/($C11-F$7))/(1+$C11)^5+Assumptions!$D$10)/Assumptions!$D$9 -> 6.1399262 | G11: =('DCF Model'!$E$16/(1+$C11)^1+'DCF Model'!$F$16/(1+$C11)^2+'DCF Model'!$G$16/(1+$C11)^3+'DCF Model'!$H$16/(1+$C11)^4+'DCF Model'!$I$16/(1+$C11)^5+('DCF Model'!$I$16*(1+G$7)/($C11-G$7))/(1+$C11)^5+Assumptions!$D$10)/Assumptions!$D$9 -> 6.466547 | H11: =('DCF Model'!$E$16/(1+$C11)^1+'DCF Model'!$F$16/(1+$C11)^2+'DCF Model'!$G$16/(1+$C11)^3+'DCF Model'!$H$16/(1+$C11)^4+'DCF Model'!$I$16/(1+$C11)^5+('DCF Model'!$I$16*(1+H$7)/($C11-H$7))/(1+$C11)^5+Assumptions!$D$10)/Assumptions!$D$9 -> 6.8525535
C12: 0.095 | D12: =('DCF Model'!$E$16/(1+$C12)^1+'DCF Model'!$F$16/(1+$C12)^2+'DCF Model'!$G$16/(1+$C12)^3+'DCF Model'!$H$16/(1+$C12)^4+'DCF Model'!$I$16/(1+$C12)^5+('DCF Model'!$I$16*(1+D$7)/($C12-D$7))/(1+$C12)^5+Assumptions!$D$10)/Assumptions!$D$9 -> 5.33615 | E12: =('DCF Model'!$E$16/(1+$C12)^1+'DCF Model'!$F$16/(1+$C12)^2+'DCF Model'!$G$16/(1+$C12)^3+'DCF Model'!$H$16/(1+$C12)^4+'DCF Model'!$I$16/(1+$C12)^5+('DCF Model'!$I$16*(1+E$7)/($C12-E$7))/(1+$C12)^5+Assumptions!$D$10)/Assumptions!$D$9 -> 5.5446023 | F12: =('DCF Model'!$E$16/(1+$C12)^1+'DCF Model'!$F$16/(1+$C12)^2+'DCF Model'!$G$16/(1+$C12)^3+'DCF Model'!$H$16/(1+$C12)^4+'DCF Model'!$I$16/(1+$C12)^5+('DCF Model'!$I$16*(1+F$7)/($C12-F$7))/(1+$C12)^5+Assumptions!$D$10)/Assumptions!$D$9 -> 5.7828335 | G12: =('DCF Model'!$E$16/(1+$C12)^1+'DCF Model'!$F$16/(1+$C12)^2+'DCF Model'!$G$16/(1+$C12)^3+'DCF Model'!$H$16/(1+$C12)^4+'DCF Model'!$I$16/(1+$C12)^5+('DCF Model'!$I$16*(1+G$7)/($C12-G$7))/(1+$C12)^5+Assumptions!$D$10)/Assumptions!$D$9 -> 6.0577157 | H12: =('DCF Model'!$E$16/(1+$C12)^1+'DCF Model'!$F$16/(1+$C12)^2+'DCF Model'!$G$16/(1+$C12)^3+'DCF Model'!$H$16/(1+$C12)^4+'DCF Model'!$I$16/(1+$C12)^5+('DCF Model'!$I$16*(1+H$7)/($C12-H$7))/(1+$C12)^5+Assumptions!$D$10)/Assumptions!$D$9 -> 6.3784116
C15: The highlighted cell matches the base assumptions of 8.5% WACC and 2.5% terminal growth. This table shows why a single DCF value should be treated as a range rather than an exact price target. | D15: The highlighted cell matches the base assumptions of 8.5% WACC and 2.5% terminal growth. This table shows why a single DCF value should be treated as a range rather than an exact price target. | E15: The highlighted cell matches the base assumptions of 8.5% WACC and 2.5% terminal growth. This table shows why a single DCF value should be treated as a range rather than an exact price target. | F15: The highlighted cell matches the base assumptions of 8.5% WACC and 2.5% terminal growth. This table shows why a single DCF value should be treated as a range rather than an exact price target. | G15: The highlighted cell matches the base assumptions of 8.5% WACC and 2.5% terminal growth. This table shows why a single DCF value should be treated as a range rather than an exact price target. | H15: The highlighted cell matches the base assumptions of 8.5% WACC and 2.5% terminal growth. This table shows why a single DCF value should be treated as a range rather than an exact price target.
C16: The highlighted cell matches the base assumptions of 8.5% WACC and 2.5% terminal growth. This table shows why a single DCF value should be treated as a range rather than an exact price target. | D16: The highlighted cell matches the base assumptions of 8.5% WACC and 2.5% terminal growth. This table shows why a single DCF value should be treated as a range rather than an exact price target. | E16: The highlighted cell matches the base assumptions of 8.5% WACC and 2.5% terminal growth. This table shows why a single DCF value should be treated as a range rather than an exact price target. | F16: The highlighted cell matches the base assumptions of 8.5% WACC and 2.5% terminal growth. This table shows why a single DCF value should be treated as a range rather than an exact price target. | G16: The highlighted cell matches the base assumptions of 8.5% WACC and 2.5% terminal growth. This table shows why a single DCF value should be treated as a range rather than an exact price target. | H16: The highlighted cell matches the base assumptions of 8.5% WACC and 2.5% terminal growth. This table shows why a single DCF value should be treated as a range rather than an exact price target.
C17: The highlighted cell matches the base assumptions of 8.5% WACC and 2.5% terminal growth. This table shows why a single DCF value should be treated as a range rather than an exact price target. | D17: The highlighted cell matches the base assumptions of 8.5% WACC and 2.5% terminal growth. This table shows why a single DCF value should be treated as a range rather than an exact price target. | E17: The highlighted cell matches the base assumptions of 8.5% WACC and 2.5% terminal growth. This table shows why a single DCF value should be treated as a range rather than an exact price target. | F17: The highlighted cell matches the base assumptions of 8.5% WACC and 2.5% terminal growth. This table shows why a single DCF value should be treated as a range rather than an exact price target. | G17: The highlighted cell matches the base assumptions of 8.5% WACC and 2.5% terminal growth. This table shows why a single DCF value should be treated as a range rather than an exact price target. | H17: The highlighted cell matches the base assumptions of 8.5% WACC and 2.5% terminal growth. This table shows why a single DCF value should be treated as a range rather than an exact price target.
C18: The highlighted cell matches the base assumptions of 8.5% WACC and 2.5% terminal growth. This table shows why a single DCF value should be treated as a range rather than an exact price target. | D18: The highlighted cell matches the base assumptions of 8.5% WACC and 2.5% terminal growth. This table shows why a single DCF value should be treated as a range rather than an exact price target. | E18: The highlighted cell matches the base assumptions of 8.5% WACC and 2.5% terminal growth. This table shows why a single DCF value should be treated as a range rather than an exact price target. | F18: The highlighted cell matches the base assumptions of 8.5% WACC and 2.5% terminal growth. This table shows why a single DCF value should be treated as a range rather than an exact price target. | G18: The highlighted cell matches the base assumptions of 8.5% WACC and 2.5% terminal growth. This table shows why a single DCF value should be treated as a range rather than an exact price target. | H18: The highlighted cell matches the base assumptions of 8.5% WACC and 2.5% terminal growth. This table shows why a single DCF value should be treated as a range rather than an exact price target.
